routing_helper/__init__.py
routing_helper-0.1.dist-info/METADATA
routing_helper-0.1.dist-info/WHEEL
routing_helper-0.1.dist-info/top_level.txt
routing_helper-0.1.dist-info/RECORD
