Metadata-Version: 2.1
Name: routing-helper
Version: 0.1
Summary: Helper functions for sail_route.jl
Home-page: https://github.com/TAJD/route_helpers
Author: Thomas Dickson
Author-email: thomas.dickson@soton.ac.uk
License: MIT
Platform: UNKNOWN
Requires-Dist: xarray
Requires-Dist: xesmf
Requires-Dist: shapely
